{"assets/images/.DS_Store":["assets/images/.DS_Store"],"assets/images/drink.png":["assets/images/drink.png"],"assets/images/fb.png":["assets/images/fb.png"],"assets/images/food.png":["assets/images/food.png"],"assets/images/ilufa_logo.png":["assets/images/ilufa_logo.png"],"assets/images/line.png":["assets/images/line.png"],"assets/images/menu01.jpg":["assets/images/menu01.jpg"],"assets/images/menu02.jpg":["assets/images/menu02.jpg"],"assets/images/menu03.jpg":["assets/images/menu03.jpg"],"assets/images/menu04.jpg":["assets/images/menu04.jpg"],"assets/images/promote01.png":["assets/images/promote01.png"],"assets/images/promote02.png":["assets/images/promote02.png"],"packages/cupertino_icons/assets/CupertinoIcons.ttf":["packages/cupertino_icons/assets/CupertinoIcons.ttf"]}